LICENSE.txt
MANIFEST.in
README.md
setup.py
PracticeWordament.egg-info/PKG-INFO
PracticeWordament.egg-info/SOURCES.txt
PracticeWordament.egg-info/dependency_links.txt
PracticeWordament.egg-info/requires.txt
PracticeWordament.egg-info/top_level.txt
practicewordament/__init__.py
practicewordament/practicewordament.py
practicewordament/utils/__init__.py
practicewordament/utils/__init__.pyc
practicewordament/utils/utils.py
practicewordament/utils/utils.pyc
practicewordament/utils/words.dump
practicewordament/utils/images/alphabet/Thumbs.db
practicewordament/utils/images/alphabet/a.png
practicewordament/utils/images/alphabet/b.png
practicewordament/utils/images/alphabet/c.png
practicewordament/utils/images/alphabet/d.png
practicewordament/utils/images/alphabet/e.png
practicewordament/utils/images/alphabet/f.png
practicewordament/utils/images/alphabet/g.png
practicewordament/utils/images/alphabet/h.png
practicewordament/utils/images/alphabet/i.png
practicewordament/utils/images/alphabet/j.png
practicewordament/utils/images/alphabet/k.png
practicewordament/utils/images/alphabet/l.png
practicewordament/utils/images/alphabet/m.png
practicewordament/utils/images/alphabet/n.png
practicewordament/utils/images/alphabet/o.png
practicewordament/utils/images/alphabet/p.png
practicewordament/utils/images/alphabet/q.png
practicewordament/utils/images/alphabet/r.png
practicewordament/utils/images/alphabet/s.png
practicewordament/utils/images/alphabet/t.png
practicewordament/utils/images/alphabet/u.png
practicewordament/utils/images/alphabet/v.png
practicewordament/utils/images/alphabet/w.png
practicewordament/utils/images/alphabet/x.png
practicewordament/utils/images/alphabet/y.png
practicewordament/utils/images/alphabet/z.png
practicewordament/utils/images/skins/1.jpg
practicewordament/utils/images/skins/2.jpg
practicewordament/utils/images/skins/3.jpg
practicewordament/utils/images/skins/Thumbs.db
practicewordament/utils/sounds/alarm.wav