Metadata-Version: 1.0
Name: PracticeWordament
Version: 1.0
Summary: A mimic of the popular word game Wordament
Home-page: http://pypi.python.org/gravetii/PracticeWordament
Author: Sandeep Dasika
Author-email: dasika.sandy@gmail.com
License: This app is released under the MIT License
